mlx_lm/__init__.py
mlx_lm/__main__.py
mlx_lm/_version.py
mlx_lm/benchmark.py
mlx_lm/cache_prompt.py
mlx_lm/chat.py
mlx_lm/convert.py
mlx_lm/evaluate.py
mlx_lm/fuse.py
mlx_lm/generate.py
mlx_lm/gguf.py
mlx_lm/lora.py
mlx_lm/manage.py
mlx_lm/perplexity.py
mlx_lm/py.typed
mlx_lm/sample_utils.py
mlx_lm/server.py
mlx_lm/tokenizer_utils.py
mlx_lm/upload.py
mlx_lm/utils.py
mlx_lm/chat_templates/__init__.py
mlx_lm/chat_templates/deepseek_v32.py
mlx_lm/models/Klear.py
mlx_lm/models/__init__.py
mlx_lm/models/activations.py
mlx_lm/models/afm7.py
mlx_lm/models/afmoe.py
mlx_lm/models/apertus.py
mlx_lm/models/baichuan_m1.py
mlx_lm/models/bailing_moe.py
mlx_lm/models/bailing_moe_linear.py
mlx_lm/models/base.py
mlx_lm/models/bitlinear_layers.py
mlx_lm/models/bitnet.py
mlx_lm/models/cache.py
mlx_lm/models/cohere.py
mlx_lm/models/cohere2.py
mlx_lm/models/dbrx.py
mlx_lm/models/deepseek.py
mlx_lm/models/deepseek_v2.py
mlx_lm/models/deepseek_v3.py
mlx_lm/models/deepseek_v32.py
mlx_lm/models/dots1.py
mlx_lm/models/ernie4_5.py
mlx_lm/models/ernie4_5_moe.py
mlx_lm/models/exaone.py
mlx_lm/models/exaone4.py
mlx_lm/models/exaone_moe.py
mlx_lm/models/falcon_h1.py
mlx_lm/models/gated_delta.py
mlx_lm/models/gemma.py
mlx_lm/models/gemma2.py
mlx_lm/models/gemma3.py
mlx_lm/models/gemma3_text.py
mlx_lm/models/gemma3n.py
mlx_lm/models/glm.py
mlx_lm/models/glm4.py
mlx_lm/models/glm4_moe.py
mlx_lm/models/glm4_moe_lite.py
mlx_lm/models/gpt2.py
mlx_lm/models/gpt_bigcode.py
mlx_lm/models/gpt_neox.py
mlx_lm/models/gpt_oss.py
mlx_lm/models/granite.py
mlx_lm/models/granitemoe.py
mlx_lm/models/granitemoehybrid.py
mlx_lm/models/helium.py
mlx_lm/models/hunyuan.py
mlx_lm/models/hunyuan_v1_dense.py
mlx_lm/models/internlm2.py
mlx_lm/models/internlm3.py
mlx_lm/models/iquestloopcoder.py
mlx_lm/models/jamba.py
mlx_lm/models/kimi_linear.py
mlx_lm/models/kimi_vl.py
mlx_lm/models/lfm2-vl.py
mlx_lm/models/lfm2.py
mlx_lm/models/lfm2_moe.py
mlx_lm/models/lille-130m.py
mlx_lm/models/llama.py
mlx_lm/models/llama4.py
mlx_lm-0.30.5.dist-info/licenses/LICENSE
mlx_lm-0.30.5.dist-info/METADATA
mlx_lm-0.30.5.dist-info/WHEEL
mlx_lm-0.30.5.dist-info/entry_points.txt
mlx_lm-0.30.5.dist-info/top_level.txt
mlx_lm-0.30.5.dist-info/RECORD
