Metadata-Version: 2.4
Name: mlx-lm
Version: 0.30.5
Summary: LLMs with MLX and the Hugging Face Hub
Home-page: https://github.com/ml-explore/mlx-lm
Author: MLX Contributors
Author-email: mlx@group.apple.com
License: MIT
Requires-Python: >=3.8
License-File: LICENSE
Requires-Dist: mlx>=0.30.3; platform_system == "Darwin"
Requires-Dist: numpy
Requires-Dist: transformers==5.0.0rc3
Requires-Dist: sentencepiece
Requires-Dist: protobuf
Requires-Dist: pyyaml
Requires-Dist: jinja2
Provides-Extra: test
Requires-Dist: datasets; extra == "test"
Requires-Dist: lm-eval; extra == "test"
Provides-Extra: train
Requires-Dist: datasets; extra == "train"
Requires-Dist: tqdm; extra == "train"
Provides-Extra: evaluate
Requires-Dist: lm-eval; extra == "evaluate"
Requires-Dist: tqdm; extra == "evaluate"
Provides-Extra: cuda13
Requires-Dist: mlx[cuda13]>=0.30.3; extra == "cuda13"
Provides-Extra: cuda12
Requires-Dist: mlx[cuda12]>=0.30.3; extra == "cuda12"
Provides-Extra: cpu
Requires-Dist: mlx[cpu]>=0.30.3; extra == "cpu"
Dynamic: author
Dynamic: author-email
Dynamic: description
Dynamic: description-content-type
Dynamic: home-page
Dynamic: license
Dynamic: license-file
Dynamic: provides-extra
Dynamic: requires-dist
Dynamic: requires-python
Dynamic: summary
